deeppavlov_kg/__init__.py
deeppavlov_kg/core/__init__.py
deeppavlov_kg/core/graph.py
deeppavlov_kg/core/ontology.py
deeppavlov_kg/core/querymaker.py
deeppavlov_kg/mocks/__init__.py
deeppavlov_kg/mocks/generate_data.py
deeppavlov_kg/mocks/generate_dataset.py
deeppavlov_kg/mocks/mock.py
deeppavlov_kg/mocks/mock_base.py
deeppavlov_kg/mocks/mock_data_generator.py
deeppavlov_kg/utils/__init__.py
deeppavlov_kg/utils/settings.py
deeppavlov_kg-0.1.1.dist-info/LICENSE
deeppavlov_kg-0.1.1.dist-info/METADATA
deeppavlov_kg-0.1.1.dist-info/WHEEL
deeppavlov_kg-0.1.1.dist-info/top_level.txt
deeppavlov_kg-0.1.1.dist-info/RECORD
